biobakery_workflows/__init__.py
biobakery_workflows/biobakery_workflows.py
biobakery_workflows/biobakery_workflows_databases.py
biobakery_workflows/biobakery_workflows_scripts.py
biobakery_workflows/config.py
biobakery_workflows/files.py
biobakery_workflows/utilities.py
biobakery_workflows/visualizations.py
biobakery_workflows/Rscripts/alpha_diversity.R
biobakery_workflows/Rscripts/assign_taxonomy.R
biobakery_workflows/Rscripts/beta_diversity.R
biobakery_workflows/Rscripts/const_seq_table.R
biobakery_workflows/Rscripts/dada2_version.R
biobakery_workflows/Rscripts/filter_and_trim.R
biobakery_workflows/Rscripts/identify_primers.R
biobakery_workflows/Rscripts/learn_error_rates.R
biobakery_workflows/Rscripts/mantel_test.R
biobakery_workflows/Rscripts/merge_paired_ends.R
biobakery_workflows/Rscripts/permanova_hmp2.R
biobakery_workflows/Rscripts/phylogeny.R
biobakery_workflows/Rscripts/strainphlan_ggtree_vis.R
biobakery_workflows/Rscripts/strainphlan_ordination_vis.R
biobakery_workflows/data/__init__.py
biobakery_workflows/data/strainphlan_species_gcf.tsv
biobakery_workflows/data/wmgx_methods.txt
biobakery_workflows/document_templates/16S.pmd
biobakery_workflows/document_templates/functional_dna.pmd
biobakery_workflows/document_templates/picard.pmd
biobakery_workflows/document_templates/quality_control_dada2.pmd
biobakery_workflows/document_templates/quality_control_paired_dna.pmd
biobakery_workflows/document_templates/quality_control_single_dna.pmd
biobakery_workflows/document_templates/quality_control_usearch.pmd
biobakery_workflows/document_templates/read_count_dada2.pmd
biobakery_workflows/document_templates/read_count_usearch.pmd
biobakery_workflows/document_templates/stats.pmd
biobakery_workflows/document_templates/stats_halla.pmd
biobakery_workflows/document_templates/stats_maaslin.pmd
biobakery_workflows/document_templates/stats_maaslin_stratified.pmd
biobakery_workflows/document_templates/stats_mantel_plots.pmd
biobakery_workflows-4.0.0a1.dist-info/LICENSE
biobakery_workflows-4.0.0a1.dist-info/METADATA
biobakery_workflows-4.0.0a1.dist-info/WHEEL
biobakery_workflows-4.0.0a1.dist-info/entry_points.txt
biobakery_workflows-4.0.0a1.dist-info/top_level.txt
biobakery_workflows-4.0.0a1.dist-info/RECORD
