Metadata-Version: 2.1
Name: biobakery-workflows
Version: 4.0.0a1
Summary: bioBakery workflows: A collection of meta'omic analysis workflows
Home-page: http://huttenhower.sph.harvard.edu/biobakery_workflows
Author: bioBakery workflows development team
Author-email: biobakery-users@googlegroups.com
License: MIT
Keywords: microbial,microbiome,bioinformatics,microbiology,metagenomic,metatranscriptomic,anadama2,humann,metaphlan,strainphlan
Platform: Linux
Platform: MacOS
Classifier: Programming Language :: Python
Classifier: Development Status :: 5 - Production/Stable
Classifier: Environment :: Console
Classifier: Operating System :: MacOS
Classifier: Operating System :: Unix
Classifier: Programming Language :: Python :: 2.7
Classifier: Topic :: Scientific/Engineering :: Bio-Informatics
License-File: LICENSE
Requires-Dist: anadama2 (>=0.5.2)
